winipedia_pyside/__init__.py
winipedia_pyside/dev/__init__.py
winipedia_pyside/dev/artifacts/__init__.py
winipedia_pyside/dev/artifacts/builder/__init__.py
winipedia_pyside/dev/artifacts/builder/builder.py
winipedia_pyside/dev/cli/__init__.py
winipedia_pyside/dev/cli/subcommands.py
winipedia_pyside/dev/configs/__init__.py
winipedia_pyside/dev/configs/configs.py
winipedia_pyside/py.typed
winipedia_pyside/utils/__init__.py
winipedia_pyside/utils/core/__init__.py
winipedia_pyside/utils/core/py_qiodevice.py
winipedia_pyside/utils/ui/__init__.py
winipedia_pyside/utils/ui/base/__init__.py
winipedia_pyside/utils/ui/base/base.py
winipedia_pyside/utils/ui/pages/__init__.py
winipedia_pyside/utils/ui/pages/base/__init__.py
winipedia_pyside/utils/ui/pages/base/base.py
winipedia_pyside/utils/ui/pages/browser.py
winipedia_pyside/utils/ui/pages/player.py
winipedia_pyside/utils/ui/widgets/__init__.py
winipedia_pyside/utils/ui/widgets/browser.py
winipedia_pyside/utils/ui/widgets/clickable_widget.py
winipedia_pyside/utils/ui/widgets/media_player.py
winipedia_pyside/utils/ui/widgets/notification.py
winipedia_pyside/utils/ui/windows/__init__.py
winipedia_pyside/utils/ui/windows/base/__init__.py
winipedia_pyside/utils/ui/windows/base/base.py
winipedia_pyside-0.2.52.dist-info/METADATA
winipedia_pyside-0.2.52.dist-info/WHEEL
winipedia_pyside-0.2.52.dist-info/entry_points.txt
winipedia_pyside-0.2.52.dist-info/licenses/LICENSE
winipedia_pyside-0.2.52.dist-info/RECORD
