Metadata-Version: 2.4
Name: winipedia-pyside
Version: 0.2.52
Summary: A package for pyside utils
License-Expression: MIT
License-File: LICENSE
Author: Winipedia
Author-email: win.steveker@gmx.de
Requires-Python: >=3.12,<3.14
Classifier: Programming Language :: Python :: 3
Classifier: Programming Language :: Python :: 3.12
Classifier: Programming Language :: Python :: 3.13
Requires-Dist: pyqt-toast-notification
Requires-Dist: pyside6
Requires-Dist: winipedia-utils
